heapcy.cpython-310-x86_64-linux-gnu.so
heapcy/__init__.pyi
heapcy/__init__.pyx
heapcy/py.typed
heapcy-0.2.1.dist-info/METADATA
heapcy-0.2.1.dist-info/WHEEL
heapcy-0.2.1.dist-info/top_level.txt
heapcy-0.2.1.dist-info/RECORD
heapcy-0.2.1.dist-info/licenses/LICENSE
